fuentes/ffd.vhd
-- Sol Ayelen Cataldo
-- FFD

entity ffd is 
	port (
		clk_i : in bit; -- clock
		rst_i : in bit; -- reset
		ena_i : in bit; -- enable
		d_i   : in bit; -- D
		q_o   : out bit -- Q
	); 
end entity ffd;

architecture ffd_arq of ffd is
begin 
	process (clk_i)
	begin
		if clk_i'event and clk_i = '1' then -- check for rising edge
			if rst_i = '1' then
				q_o <= '0'; 
			elsif ena_i = '1' then
				q_o <= d_i; 
			end if; 
		end if; 
	end process; 
end architecture;

fuentes/cont_bcd.vhd
entity cont_bcd is
	port(
		clk_i : in bit;
		rst_i : in bit;
		ena_i : in bit;
		q_o : out bit_vector(3 downto 0)
		);
	end;


architecture cont_bcd_arq of cont_bcd is
	component ffd is -- declaro el ffd
		port(
			clk_i: in bit; --clock
			rst_i: in bit; --reset
			ena_i: in bit; --enable
			d_i: in bit; -- D
			q_o: out bit -- Q
			 ); 
	end component;
	
	signal q_aux: bit_vector(3 downto 0); 
	signal d_aux: bit_vector(3 downto 0);


begin 
	d_aux(3) <= (q_aux(2) and q_aux(1) and q_aux(0)) or (q_aux(3) and not q_aux(0));
	d_aux(2) <= (q_aux(2) and not q_aux(1)) or (q_aux(2) and not q_aux(0)) or (not q_aux(2) and q_aux(1) and q_aux(0));
	d_aux(1) <= (q_aux(1) and not q_aux(0)) or (not q_aux(3) and not q_aux(1) and q_aux(0));
	d_aux(0) <= not q_aux(0);
	q_o <= q_aux;
	
	ffd_3: ffd
		port map(
			clk_i => clk_i,
			rst_i => rst_i,
			ena_i => ena_i,
			d_i => d_aux(3),
			q_o => q_aux(3)
		);
	
	ffd_2: ffd
		port map(
			clk_i => clk_i,
			rst_i => rst_i,
			ena_i => ena_i,
			d_i => d_aux(2),
			q_o => q_aux(2)
		);
		
	ffd_1: ffd
		port map(
			clk_i => clk_i,
			rst_i => rst_i,
			ena_i => ena_i,
			d_i => d_aux(1),
			q_o => q_aux(1)
		);
	
	ffd_0: ffd
		port map(
			clk_i => clk_i,
			rst_i => rst_i,
			ena_i => ena_i,
			d_i => d_aux(0),
			q_o => q_aux(0)
		);


end;

fuentes/cont_bcd_tb.vhd

entity cont_bcd_tb is
end;

architecture cont_bcd_tb_arq of cont_bcd_tb is
	component cont_bcd is
		port(
			clk_i : in bit;
			rst_i : in bit;
			ena_i : in bit;
			q_o : out bit_vector(3 downto 0)
		);
	end component;
	
	signal clk_tb: bit := '1';
	signal rst_tb: bit := '1';
	signal ena_tb: bit := '1';
	signal q_tb: bit_vector (3 downto 0);
begin
	clk_tb <= not clk_tb after 10 ns;
	rst_tb <= '0' after 10 ns;
	
	DUT: cont_bcd
		port map(
			clk_i => clk_tb,
			rst_i => rst_tb,
			ena_i => ena_tb,
			q_o => q_tb
		);
end architecture cont_bcd_tb_arq;

simulacion/cont_bcd_tb.vcd
$date
  Tue Jan  9 10:29:13 2024
$end
$version
  GHDL v0
$end
$timescale
  1 fs
$end
$scope module standard $end
$upscope $end
$scope module cont_bcd_tb $end
$var reg 1 ! clk_tb $end
$var reg 1 " rst_tb $end
$var reg 1 # ena_tb $end
$var reg 4 $ q_tb[3:0] $end
$scope module dut $end
$var reg 1 % clk_i $end
$var reg 1 & rst_i $end
$var reg 1 ' ena_i $end
$var reg 4 ( q_o[3:0] $end
$var reg 4 ) q_aux[3:0] $end
$var reg 4 * d_aux[3:0] $end
$scope module ffd_3 $end
$var reg 1 + clk_i $end
$var reg 1 , rst_i $end
$var reg 1 - ena_i $end
$var reg 1 . d_i $end
$var reg 1 / q_o $end
$upscope $end
$scope module ffd_2 $end
$var reg 1 0 clk_i $end
$var reg 1 1 rst_i $end
$var reg 1 2 ena_i $end
$var reg 1 3 d_i $end
$var reg 1 4 q_o $end
$upscope $end
$scope module ffd_1 $end
$var reg 1 5 clk_i $end
$var reg 1 6 rst_i $end
$var reg 1 7 ena_i $end
$var reg 1 8 d_i $end
$var reg 1 9 q_o $end
$upscope $end
$scope module ffd_0 $end
$var reg 1 : clk_i $end
$var reg 1 ; rst_i $end
$var reg 1 < ena_i $end
$var reg 1 = d_i $end
$var reg 1 > q_o $end
$upscope $end
$upscope $end
$upscope $end
$enddefinitions $end
#0
1!
1"
1#
b0000 $
1%
1&
1'
b0000 (
b0000 )
b0001 *
1+
1,
1-
0.
0/
10
11
12
03
04
15
16
17
08
09
1:
1;
1<
1=
0>
#10000000
0!
0"
0%
0&
0+
0,
00
01
05
06
0:
0;
#20000000
1!
b0001 $
1%
b0001 (
b0001 )
b0010 *
1+
10
15
18
1:
0=
1>
#30000000
0!
0%
0+
00
05
0:
#40000000
1!
b0010 $
1%
b0010 (
b0010 )
b0011 *
1+
10
15
19
1:
1=
0>
#50000000
0!
0%
0+
00
05
0:
#60000000
1!
b0011 $
1%
b0011 (
b0011 )
b0100 *
1+
10
13
15
08
1:
0=
1>
#70000000
0!
0%
0+
00
05
0:
#80000000
1!
b0100 $
1%
b0100 (
b0100 )
b0101 *
1+
10
14
15
09
1:
1=
0>
#90000000
0!
0%
0+
00
05
0:
#100000000
1!
b0101 $
1%
b0101 (
b0101 )
b0110 *
1+
10
15
18
1:
0=
1>
#110000000
0!
0%
0+
00
05
0:
#120000000
1!
b0110 $
1%
b0110 (
b0110 )
b0111 *
1+
10
15
19
1:
1=
0>
#130000000
0!
0%
0+
00
05
0:
#140000000
1!
b0111 $
1%
b0111 (
b0111 )
b1000 *
1+
1.
10
03
15
08
1:
0=
1>
#150000000
0!
0%
0+
00
05
0:
#160000000
1!
b1000 $
1%
b1000 (
b1000 )
b1001 *
1+
1/
10
04
15
09
1:
1=
0>
#170000000
0!
0%
0+
00
05
0:
#180000000
1!
b1001 $
1%
b1001 (
b1001 )
b0000 *
1+
0.
10
15
1:
0=
1>
#190000000
0!
0%
0+
00
05
0:
#200000000
1!
b0000 $
1%
b0000 (
b0000 )
b0001 *
1+
0/
10
15
1:
1=
0>
#210000000
0!
0%
0+
00
05
0:
#220000000
1!
b0001 $
1%
b0001 (
b0001 )
b0010 *
1+
10
15
18
1:
0=
1>
#230000000
0!
0%
0+
00
05
0:
#240000000
1!
b0010 $
1%
b0010 (
b0010 )
b0011 *
1+
10
15
19
1:
1=
0>
#250000000
0!
0%
0+
00
05
0:
#260000000
1!
b0011 $
1%
b0011 (
b0011 )
b0100 *
1+
10
13
15
08
1:
0=
1>
#270000000
0!
0%
0+
00
05
0:
#280000000
1!
b0100 $
1%
b0100 (
b0100 )
b0101 *
1+
10
14
15
09
1:
1=
0>
#290000000
0!
0%
0+
00
05
0:
#300000000
1!
b0101 $
1%
b0101 (
b0101 )
b0110 *
1+
10
15
18
1:
0=
1>
#310000000
0!
0%
0+
00
05
0:
#320000000
1!
b0110 $
1%
b0110 (
b0110 )
b0111 *
1+
10
15
19
1:
1=
0>
#330000000
0!
0%
0+
00
05
0:
#340000000
1!
b0111 $
1%
b0111 (
b0111 )
b1000 *
1+
1.
10
03
15
08
1:
0=
1>
#350000000
0!
0%
0+
00
05
0:
#360000000
1!
b1000 $
1%
b1000 (
b1000 )
b1001 *
1+
1/
10
04
15
09
1:
1=
0>
#370000000
0!
0%
0+
00
05
0:
#380000000
1!
b1001 $
1%
b1001 (
b1001 )
b0000 *
1+
0.
10
15
1:
0=
1>
#390000000
0!
0%
0+
00
05
0:
#400000000
1!
b0000 $
1%
b0000 (
b0000 )
b0001 *
1+
0/
10
15
1:
1=
0>
#410000000
0!
0%
0+
00
05
0:
#420000000
1!
b0001 $
1%
b0001 (
b0001 )
b0010 *
1+
10
15
18
1:
0=
1>
#430000000
0!
0%
0+
00
05
0:
#440000000
1!
b0010 $
1%
b0010 (
b0010 )
b0011 *
1+
10
15
19
1:
1=
0>
#450000000
0!
0%
0+
00
05
0:
#460000000
1!
b0011 $
1%
b0011 (
b0011 )
b0100 *
1+
10
13
15
08
1:
0=
1>
#470000000
0!
0%
0+
00
05
0:
#480000000
1!
b0100 $
1%
b0100 (
b0100 )
b0101 *
1+
10
14
15
09
1:
1=
0>
#490000000
0!
0%
0+
00
05
0:
#500000000
1!
b0101 $
1%
b0101 (
b0101 )
b0110 *
1+
10
15
18
1:
0=
1>
#510000000
0!
0%
0+
00
05
0:
#520000000
1!
b0110 $
1%
b0110 (
b0110 )
b0111 *
1+
10
15
19
1:
1=
0>
#530000000
0!
0%
0+
00
05
0:
#540000000
1!
b0111 $
1%
b0111 (
b0111 )
b1000 *
1+
1.
10
03
15
08
1:
0=
1>
#550000000
0!
0%
0+
00
05
0:
#560000000
1!
b1000 $
1%
b1000 (
b1000 )
b1001 *
1+
1/
10
04
15
09
1:
1=
0>
#570000000
0!
0%
0+
00
05
0:
#580000000
1!
b1001 $
1%
b1001 (
b1001 )
b0000 *
1+
0.
10
15
1:
0=
1>
#590000000
0!
0%
0+
00
05
0:
#600000000
1!
b0000 $
1%
b0000 (
b0000 )
b0001 *
1+
0/
10
15
1:
1=
0>
#610000000
0!
0%
0+
00
05
0:
#620000000
1!
b0001 $
1%
b0001 (
b0001 )
b0010 *
1+
10
15
18
1:
0=
1>
#630000000
0!
0%
0+
00
05
0:
#640000000
1!
b0010 $
1%
b0010 (
b0010 )
b0011 *
1+
10
15
19
1:
1=
0>
#650000000
0!
0%
0+
00
05
0:
#660000000
1!
b0011 $
1%
b0011 (
b0011 )
b0100 *
1+
10
13
15
08
1:
0=
1>
#670000000
0!
0%
0+
00
05
0:
#680000000
1!
b0100 $
1%
b0100 (
b0100 )
b0101 *
1+
10
14
15
09
1:
1=
0>
#690000000
0!
0%
0+
00
05
0:
#700000000
1!
b0101 $
1%
b0101 (
b0101 )
b0110 *
1+
10
15
18
1:
0=
1>
#710000000
0!
0%
0+
00
05
0:
#720000000
1!
b0110 $
1%
b0110 (
b0110 )
b0111 *
1+
10
15
19
1:
1=
0>
#730000000
0!
0%
0+
00
05
0:
#740000000
1!
b0111 $
1%
b0111 (
b0111 )
b1000 *
1+
1.
10
03
15
08
1:
0=
1>
#750000000
0!
0%
0+
00
05
0:
#760000000
1!
b1000 $
1%
b1000 (
b1000 )
b1001 *
1+
1/
10
04
15
09
1:
1=
0>
#770000000
0!
0%
0+
00
05
0:
#780000000
1!
b1001 $
1%
b1001 (
b1001 )
b0000 *
1+
0.
10
15
1:
0=
1>
#790000000
0!
0%
0+
00
05
0:
#800000000
1!
b0000 $
1%
b0000 (
b0000 )
b0001 *
1+
0/
10
15
1:
1=
0>
#810000000
0!
0%
0+
00
05
0:
#820000000
1!
b0001 $
1%
b0001 (
b0001 )
b0010 *
1+
10
15
18
1:
0=
1>
#830000000
0!
0%
0+
00
05
0:
#840000000
1!
b0010 $
1%
b0010 (
b0010 )
b0011 *
1+
10
15
19
1:
1=
0>
#850000000
0!
0%
0+
00
05
0:
#860000000
1!
b0011 $
1%
b0011 (
b0011 )
b0100 *
1+
10
13
15
08
1:
0=
1>
#870000000
0!
0%
0+
00
05
0:
#880000000
1!
b0100 $
1%
b0100 (
b0100 )
b0101 *
1+
10
14
15
09
1:
1=
0>
#890000000
0!
0%
0+
00
05
0:
#900000000
1!
b0101 $
1%
b0101 (
b0101 )
b0110 *
1+
10
15
18
1:
0=
1>
#910000000
0!
0%
0+
00
05
0:
#920000000
1!
b0110 $
1%
b0110 (
b0110 )
b0111 *
1+
10
15
19
1:
1=
0>
#930000000
0!
0%
0+
00
05
0:
#940000000
1!
b0111 $
1%
b0111 (
b0111 )
b1000 *
1+
1.
10
03
15
08
1:
0=
1>
#950000000
0!
0%
0+
00
05
0:
#960000000
1!
b1000 $
1%
b1000 (
b1000 )
b1001 *
1+
1/
10
04
15
09
1:
1=
0>
#970000000
0!
0%
0+
00
05
0:
#980000000
1!
b1001 $
1%
b1001 (
b1001 )
b0000 *
1+
0.
10
15
1:
0=
1>
#990000000
0!
0%
0+
00
05
0:
#1000000000
1!
b0000 $
1%
b0000 (
b0000 )
b0001 *
1+
0/
10
15
1:
1=
0>
